[
  {
    "text": "аззз",
    "author": "guest_1327",
    "rot": -0.05780940673718593,
    "date": 1780067809728,
    "id": "note_seed_01",
    "createdAt": "2026-05-29T15:16:49.728000Z"
  },
  {
    "text": "йоу",
    "author": "guest_1938",
    "rot": -1.483441331860174,
    "date": 1780067598007,
    "id": "note_seed_02",
    "createdAt": "2026-05-29T15:13:18.007000Z"
  },
  {
    "text": "Awesome portfolio! Love the terminal vibe 🔥",
    "author": "anon_dev",
    "rot": -1,
    "id": "note_seed_03",
    "createdAt": "2026-05-29T23:58:00Z",
    "date": 1780099080000
  },
  {
    "text": "Waiting for UMA beta release. Need a solid secure messenger.",
    "author": "crypto_guy",
    "rot": 1.5,
    "id": "note_seed_04",
    "createdAt": "2026-05-29T23:57:00Z",
    "date": 1780099020000
  },
  {
    "text": "Nice ASCII art implementation. Smooth af.",
    "author": "neo",
    "rot": -2,
    "id": "note_seed_05",
    "createdAt": "2026-05-29T23:56:00Z",
    "date": 1780098960000
  },
  {
    "text": "Frontend looks dope, what font is that? 🤔",
    "author": "designer12",
    "rot": 1,
    "id": "note_seed_06",
    "createdAt": "2026-05-29T23:55:00Z",
    "date": 1780098900000
  },
  {
    "text": "Привет из КЗ! Успехов с проектами 🇰🇿",
    "author": "almaty_coder",
    "rot": -0.5,
    "id": "note_seed_07",
    "createdAt": "2026-05-29T23:54:00Z",
    "date": 1780098840000
  }
]
